Metadata-Version: 2.1
Name: pyopae
Version: 1.0.0
Summary: OPAE python API
Home-page: https://gitlab.devtools.intel.com/OPAE/pyopae
Author: Wei Huang
Author-email: wei.huang@intel.com
License: BSD3
Keywords: DPDK OPAE API wrapper
Platform: Linux
Classifier: Programming Language :: C
Classifier: License :: OSI Approved :: BSD License
Classifier: Operating System :: POSIX :: Linux
Requires-Python: >=3.6
